{
  "version": "1.0.0",
  "producer": "Java AppCAT CLI",
  "metadata": {
    "analysisStartTime": "2026-02-19T18:17:56.7662746Z",
    "analysisEndTime": "2026-02-19T19:03:58.3577905Z",
    "status": "completed",
    "privacyMode": "Protected",
    "privacyModeHelpUrl": "https://aka.ms/appcat-privacy-mode",
    "targetIds": [
      "azure-aks",
      "azure-appservice",
      "azure-container-apps"
    ],
    "targetDisplayNames": [
      "Azure Kubernetes Service",
      "Azure App Service",
      "Azure Container Apps"
    ],
    "capabilities": [],
    "os": [],
    "id": "20260219191756",
    "name": "Report_20260219191756",
    "domains": [
      "cloud-readiness",
      "java-upgrade"
    ],
    "mode": "issue-only"
  },
  "summary": {
    "totalProjects": 1,
    "totalIssues": 5,
    "totalIncidents": 14,
    "totalEffort": 46,
    "charts": {
      "severity": {
        "mandatory": 7,
        "optional": 5,
        "potential": 2,
        "information": 0
      },
      "category": {
        "local-resource-access": 2,
        "remote-communication": 10,
        "spring-migration": 2
      }
    },
    "security": {}
  },
  "projects": [
    {
      "path": ".",
      "issues": 5,
      "storyPoints": 46,
      "properties": {
        "appName": "ai-trading-system",
        "jdkVersion": "17",
        "frameworks": [
          "Flask",
          "Spring Boot",
          "Spring"
        ],
        "languages": [
          "Python",
          "Java"
        ],
        "tools": [
          "Maven"
        ]
      },
      "incidents": [
        {
          "ruleId": "spring-boot-to-azure-port-01000",
          "incidentId": "fb1ef0c2-6c47-4d3d-a25b-49df3a1501fb",
          "location": "java-frontend/src/main/resources/application.properties",
          "locationKind": "File",
          "line": 2,
          "column": 0,
          "targets": {
            "azure-aks": {
              "effort": 1,
              "severity": "potential"
            },
            "azure-appservice": {
              "effort": 1,
              "severity": "potential"
            },
            "azure-container-apps": {
              "effort": 1,
              "severity": "potential"
            }
          },
          "labels": [
            "type=violation",
            "ruleset=azure/springboot"
          ]
        },
        {
          "ruleId": "spring-boot-to-azure-restricted-config-01000",
          "incidentId": "917cf3fc-3d65-4a8a-b4e3-d82d59dce71b",
          "location": "java-frontend/src/main/resources/application.properties",
          "locationKind": "File",
          "line": 2,
          "column": 0,
          "targets": {
            "azure-container-apps": {
              "effort": 1,
              "severity": "potential"
            }
          },
          "labels": [
            "type=violation",
            "ruleset=azure/springboot"
          ]
        },
        {
          "ruleId": "localhost-http-00001",
          "incidentId": "5ed7948a-5536-4089-b968-17dd06005a26",
          "location": "java-frontend/src/main/resources/application.properties",
          "locationKind": "File",
          "line": 5,
          "column": 0,
          "targets": {
            "azure-aks": {
              "effort": 7,
              "severity": "mandatory"
            },
            "azure-appservice": {
              "effort": 7,
              "severity": "mandatory"
            },
            "azure-container-apps": {
              "effort": 7,
              "severity": "mandatory"
            }
          },
          "labels": [
            "type=violation",
            "ruleset=cloud-readiness"
          ]
        },
        {
          "ruleId": "localhost-http-00001",
          "incidentId": "dc51034c-aca3-4198-bfb2-63d9bf708280",
          "location": "java-frontend/src/main/java/com/aitrading/service/TradingApiService.java",
          "locationKind": "File",
          "line": 18,
          "column": 0,
          "targets": {
            "azure-aks": {
              "effort": 7,
              "severity": "mandatory"
            },
            "azure-appservice": {
              "effort": 7,
              "severity": "mandatory"
            },
            "azure-container-apps": {
              "effort": 7,
              "severity": "mandatory"
            }
          },
          "labels": [
            "type=violation",
            "ruleset=cloud-readiness"
          ]
        },
        {
          "ruleId": "unsecure-network-protocol-00000",
          "incidentId": "60fbc8dc-64bf-4a76-874a-f81b32a9397b",
          "location": "java-frontend/src/main/resources/application.properties",
          "locationKind": "File",
          "line": 5,
          "column": 0,
          "targets": {
            "azure-aks": {
              "effort": 3,
              "severity": "mandatory"
            },
            "azure-appservice": {
              "effort": 3,
              "severity": "mandatory"
            },
            "azure-container-apps": {
              "effort": 3,
              "severity": "mandatory"
            }
          },
          "labels": [
            "type=violation",
            "ruleset=cloud-readiness"
          ]
        },
        {
          "ruleId": "unsecure-network-protocol-00000",
          "incidentId": "011a7801-d72b-4f52-b233-e846133e4bd5",
          "location": "docker-compose.yml",
          "locationKind": "File",
          "line": 69,
          "column": 0,
          "targets": {
            "azure-aks": {
              "effort": 3,
              "severity": "mandatory"
            },
            "azure-appservice": {
              "effort": 3,
              "severity": "mandatory"
            },
            "azure-container-apps": {
              "effort": 3,
              "severity": "mandatory"
            }
          },
          "labels": [
            "type=violation",
            "ruleset=cloud-readiness"
          ]
        },
        {
          "ruleId": "unsecure-network-protocol-00000",
          "incidentId": "dd46c8d0-9687-4bf7-b9c4-fe145a0b2d4d",
          "location": "docker-compose.yml",
          "locationKind": "File",
          "line": 98,
          "column": 0,
          "targets": {
            "azure-aks": {
              "effort": 3,
              "severity": "mandatory"
            },
            "azure-appservice": {
              "effort": 3,
              "severity": "mandatory"
            },
            "azure-container-apps": {
              "effort": 3,
              "severity": "mandatory"
            }
          },
          "labels": [
            "type=violation",
            "ruleset=cloud-readiness"
          ]
        },
        {
          "ruleId": "unsecure-network-protocol-00000",
          "incidentId": "ed4c3998-1c42-4e30-8b0e-88ade1e9f595",
          "location": "docker-compose.hedgefund.yml",
          "locationKind": "File",
          "line": 60,
          "column": 0,
          "targets": {
            "azure-aks": {
              "effort": 3,
              "severity": "mandatory"
            },
            "azure-appservice": {
              "effort": 3,
              "severity": "mandatory"
            },
            "azure-container-apps": {
              "effort": 3,
              "severity": "mandatory"
            }
          },
          "labels": [
            "type=violation",
            "ruleset=cloud-readiness"
          ]
        },
        {
          "ruleId": "unsecure-network-protocol-00000",
          "incidentId": "ae98e030-c94b-410a-9765-ad85a03db55e",
          "location": "java-frontend/src/main/java/com/aitrading/service/TradingApiService.java",
          "locationKind": "File",
          "line": 18,
          "column": 0,
          "targets": {
            "azure-aks": {
              "effort": 3,
              "severity": "mandatory"
            },
            "azure-appservice": {
              "effort": 3,
              "severity": "mandatory"
            },
            "azure-container-apps": {
              "effort": 3,
              "severity": "mandatory"
            }
          },
          "labels": [
            "type=violation",
            "ruleset=cloud-readiness"
          ]
        },
        {
          "ruleId": "hardcoded-urls-00001",
          "incidentId": "8467462c-f7b9-465e-bba7-4e86b9fdb903",
          "location": "docker-compose.yml",
          "locationKind": "File",
          "line": 69,
          "column": 0,
          "targets": {
            "azure-aks": {
              "effort": 3,
              "severity": "optional"
            },
            "azure-appservice": {
              "effort": 3,
              "severity": "optional"
            },
            "azure-container-apps": {
              "effort": 3,
              "severity": "optional"
            }
          },
          "labels": [
            "type=violation",
            "ruleset=cloud-readiness"
          ]
        },
        {
          "ruleId": "hardcoded-urls-00001",
          "incidentId": "40d0a926-3eb4-4f13-a499-38486f57a4e8",
          "location": "docker-compose.yml",
          "locationKind": "File",
          "line": 98,
          "column": 0,
          "targets": {
            "azure-aks": {
              "effort": 3,
              "severity": "optional"
            },
            "azure-appservice": {
              "effort": 3,
              "severity": "optional"
            },
            "azure-container-apps": {
              "effort": 3,
              "severity": "optional"
            }
          },
          "labels": [
            "type=violation",
            "ruleset=cloud-readiness"
          ]
        },
        {
          "ruleId": "hardcoded-urls-00001",
          "incidentId": "393b3dae-cbd2-4e30-a663-b73686e62476",
          "location": "docker-compose.hedgefund.yml",
          "locationKind": "File",
          "line": 60,
          "column": 0,
          "targets": {
            "azure-aks": {
              "effort": 3,
              "severity": "optional"
            },
            "azure-appservice": {
              "effort": 3,
              "severity": "optional"
            },
            "azure-container-apps": {
              "effort": 3,
              "severity": "optional"
            }
          },
          "labels": [
            "type=violation",
            "ruleset=cloud-readiness"
          ]
        },
        {
          "ruleId": "hardcoded-urls-00001",
          "incidentId": "aef6e848-caac-4560-aa3f-768a5c934cd3",
          "location": "java-frontend/src/main/resources/application.properties",
          "locationKind": "File",
          "line": 5,
          "column": 0,
          "targets": {
            "azure-aks": {
              "effort": 3,
              "severity": "optional"
            },
            "azure-appservice": {
              "effort": 3,
              "severity": "optional"
            },
            "azure-container-apps": {
              "effort": 3,
              "severity": "optional"
            }
          },
          "labels": [
            "type=violation",
            "ruleset=cloud-readiness"
          ]
        },
        {
          "ruleId": "hardcoded-urls-00001",
          "incidentId": "78988781-342d-4bb8-a55f-ee63c968ade1",
          "location": "java-frontend/src/main/java/com/aitrading/service/TradingApiService.java",
          "locationKind": "File",
          "line": 18,
          "column": 0,
          "targets": {
            "azure-aks": {
              "effort": 3,
              "severity": "optional"
            },
            "azure-appservice": {
              "effort": 3,
              "severity": "optional"
            },
            "azure-container-apps": {
              "effort": 3,
              "severity": "optional"
            }
          },
          "labels": [
            "type=violation",
            "ruleset=cloud-readiness"
          ]
        }
      ]
    }
  ],
  "rules": {
    "hardcoded-urls-00001": {
      "id": "hardcoded-urls-00001",
      "description": "This patterns verifies in source code and configuration files the presence of hardcoded URLs using the HTTP protocol (HTTP/HTTPS). This URL would need to be replaced by the new resource's URL during the Cloud migration, if any change occured.",
      "title": "Avoid using hardcoded URLs (HTTP protocol) in source code",
      "severity": "optional",
      "effort": 3,
      "labels": [
        "target=azure-aks",
        "target=azure-container-apps",
        "target=azure-appservice",
        "source",
        "domain=cloud-readiness",
        "category=remote-communication",
        "os=windows",
        "os=linux"
      ]
    },
    "localhost-http-00001": {
      "id": "localhost-http-00001",
      "description": "The app is trying to access local resource by HTTP, please try to migrate the resource to cloud",
      "title": "Local HTTP Calls",
      "severity": "mandatory",
      "effort": 7,
      "labels": [
        "target=azure-aks",
        "target=azure-container-apps",
        "target=azure-appservice",
        "capability=containerization",
        "source",
        "domain=cloud-readiness",
        "category=local-resource-access",
        "localhost",
        "containerization",
        "os=windows",
        "os=linux"
      ]
    },
    "spring-boot-to-azure-port-01000": {
      "id": "spring-boot-to-azure-port-01000",
      "description": "The application is setting the server port. To migrate a Java application that sets the server port to Azure Container Apps:\n\n * **Azure Container Apps allows you to expose port according to your Azure Container Apps resource configuration. For instance, a Spring Boot application listens to port of 8080 by default, but it can be set with server.port or environment variable SERVER_PORT as you need.",
      "title": "Server port configuration found",
      "severity": "potential",
      "effort": 1,
      "links": [
        {
          "url": "https://learn.microsoft.com/azure/developer/java/migration/migrate-spring-boot-to-azure-container-apps#identify-any-clients-relying-on-a-non-standard-port",
          "title": "Identify any clients relying on a non-standard port"
        }
      ],
      "labels": [
        "source=springboot",
        "target=azure-aks",
        "target=azure-appservice",
        "target=azure-container-apps",
        "domain=cloud-readiness",
        "category=spring-migration",
        "port",
        "server port",
        "os=windows",
        "os=linux"
      ]
    },
    "spring-boot-to-azure-restricted-config-01000": {
      "id": "spring-boot-to-azure-restricted-config-01000",
      "description": "The application uses restricted configurations for Azure Container Apps.\n These properties can be automatically injected into your application environment by Azure Container Apps to access managed Config Server and managed Eureka Server.\n Please remove them from your application, including configuration files, config server files, command line parameters, Java system attributes, and environment variables.\n\n If configured in **configuration files**: they will be ignored and overrided by Azure Container Apps.\n \n If configured in **Config Server files**, **command line parameters**, **Java system attribute**, **environment variable**: they need to be removed or you might experience conflicts and unexpected behavior.",
      "title": "Restricted configurations found",
      "severity": "potential",
      "effort": 1,
      "links": [
        {
          "url": "https://learn.microsoft.com/azure/developer/java/migration/migrate-spring-cloud-to-azure-container-apps#remove-restricted-configurations",
          "title": "Migrate Spring Boot applications to Azure Container Apps - Remove restricted configurations"
        },
        {
          "url": "https://learn.microsoft.com/azure/container-apps/java-config-server?tabs=azure-cli",
          "title": "Connect to a managed Config Server for Spring in Azure Container Apps"
        },
        {
          "url": "https://learn.microsoft.com/azure/container-apps/java-eureka-server?tabs=azure-cli",
          "title": "Connect to a managed Eureka Server for Spring in Azure Container Apps"
        }
      ],
      "labels": [
        "target=azure-container-apps",
        "source=springboot",
        "domain=cloud-readiness",
        "category=spring-migration",
        "os=windows",
        "os=linux"
      ]
    },
    "unsecure-network-protocol-00000": {
      "id": "unsecure-network-protocol-00000",
      "description": "Using secured protocols such as HTTPS and SFTP (over HTTP and FTP) should now be the norm as applications are more and more exposed and interconnected. \nThis CloudReady patterns looks for unescured URI in the source code or deprecated URI libraries. \nIdeally, URLs should be replaced in your source code by secured protocols HTTPS and SFTP (and ensure the infrastructure implements these protocols for the resources your application calls, uses or references).",
      "title": "Use of unsecured network protocols or URI libraries",
      "severity": "mandatory",
      "effort": 3,
      "links": [
        {
          "url": "https://developers.google.com/web/fundamentals/security/encrypt-in-transit/why-https",
          "title": "Why HTTPS matters"
        },
        {
          "url": "https://www.ssh.com/ssh/sftp/",
          "title": "SSH File Transfer Protocol (SFTP): Get SFTP client & server"
        }
      ],
      "labels": [
        "target=azure-aks",
        "target=azure-container-apps",
        "target=azure-appservice",
        "capability=containerization",
        "source",
        "domain=cloud-readiness",
        "category=remote-communication",
        "containerization",
        "os=windows",
        "os=linux"
      ]
    }
  },
  "security": []
}